LICENSE
MANIFEST.in
README.rst
requirements.txt
setup.py
test-requirements.txt
tox.ini
stepmaker/__init__.py
stepmaker/addresses.py
stepmaker/environment.py
stepmaker/exceptions.py
stepmaker/redaction.py
stepmaker/specials.py
stepmaker/steps.py
stepmaker/utils.py
stepmaker.egg-info/PKG-INFO
stepmaker.egg-info/SOURCES.txt
stepmaker.egg-info/dependency_links.txt
stepmaker.egg-info/requires.txt
stepmaker.egg-info/top_level.txt
tests/__init__.py
tests/unit/__init__.py
tests/unit/test_addresses.py
tests/unit/test_environment.py
tests/unit/test_exceptions.py
tests/unit/test_redaction.py
tests/unit/test_specials.py
tests/unit/test_steps.py
tests/unit/test_utils.py